telegram_messager/__init__.py
telegram_messager/__main__.py
telegram_messager/main.py
telegram_messager-0.0.3.dist-info/METADATA
telegram_messager-0.0.3.dist-info/WHEEL
telegram_messager-0.0.3.dist-info/entry_points.txt
telegram_messager-0.0.3.dist-info/top_level.txt
telegram_messager-0.0.3.dist-info/RECORD
