Metadata-Version: 2.1
Name: telegram-messager
Version: 0.0.3
Summary: Simplest util to send messages and documents to Telegram
Home-page: https://github.com/PasaOpasen/telegram-messager
Author: Demetry Pascal
Author-email: qtckpuhdsa@gmail.com
Maintainer: Demetry Pascal
License: MIT
Keywords: telegram,bot
Classifier: Programming Language :: Python :: 3.8
Classifier: License :: OSI Approved :: MIT License
Classifier: Operating System :: OS Independent
Classifier: Topic :: Software Development :: Libraries :: Python Modules
Requires-Dist: requests
Requires-Dist: typing-extensions
